streamlit_slickgrid/__init__.py
streamlit_slickgrid/frontend/build/asset-manifest.json
streamlit_slickgrid/frontend/build/bootstrap.min.css
streamlit_slickgrid/frontend/build/index.html
streamlit_slickgrid/frontend/build/static/css/main.262d0d7e.css
streamlit_slickgrid/frontend/build/static/css/main.262d0d7e.css.map
streamlit_slickgrid/frontend/build/static/js/main.9adad6e1.js
streamlit_slickgrid/frontend/build/static/js/main.9adad6e1.js.LICENSE.txt
streamlit_slickgrid/frontend/build/static/js/main.9adad6e1.js.map
streamlit_slickgrid-0.2.0.dist-info/METADATA
streamlit_slickgrid-0.2.0.dist-info/WHEEL
streamlit_slickgrid-0.2.0.dist-info/top_level.txt
streamlit_slickgrid-0.2.0.dist-info/RECORD
