Metadata-Version: 2.4
Name: streamlit-slickgrid
Version: 0.2.0
Summary: A Streamlit component that wraps SlickGrid
Author-email: Thiago Teixeira <thiago.teixeira@snowflake.com>
License: Apache 2.0
Requires-Python: >=3.9.0
Requires-Dist: streamlit>=1.40.0
